LICENSE
MANIFEST.in
README.rst
VERSION
postgresql-requirements.txt
requirements.txt
setup.py
src/python_tempo.egg-info/PKG-INFO
src/python_tempo.egg-info/SOURCES.txt
src/python_tempo.egg-info/dependency_links.txt
src/python_tempo.egg-info/entry_points.txt
src/python_tempo.egg-info/requires.txt
src/python_tempo.egg-info/top_level.txt
src/tempo/__init__.py
src/tempo/recurrentevent.py
src/tempo/recurrenteventset.py
src/tempo/sparseinterval.py
src/tempo/timeutils.py
src/tempo/unit.py
src/tempo/utils.py
src/tempo/django/__init__.py
src/tempo/django/fields.py
src/tempo/postgresql/__init__.py
src/tempo/postgresql/install.py
src/tempo/postgresql/install.sql
src/tempo/postgresql/uninstall.py
src/tempo/postgresql/uninstall.sql
src/tempo/rest_framework/__init__.py
src/tempo/rest_framework/serializers.py