Metadata-Version: 1.1
Name: python-tempo
Version: 0.1.0
Summary: Scheduling library, that provides a generic way to compose and query schedules of recurrent continuous events, such as working time of organizations, meetings, movie shows, etc.
Home-page: https://github.com/AndrewPashkin/python-tempo/
Author: Andrew Pashkin
Author-email: andrew.pashkin@gmx.co.uk
License: BSD
Platform: UNKNOWN
Classifier: Development Status :: 4 - Beta
Classifier: Intended Audience :: Developers
Classifier: License :: OSI Approved :: BSD License
Classifier: Programming Language :: Python
Classifier: Operating System :: MacOS :: MacOS X
Classifier: Operating System :: Microsoft :: Windows
Classifier: Operating System :: POSIX
Classifier: Programming Language :: Python :: 2
Classifier: Programming Language :: Python :: 2.6
Classifier: Programming Language :: Python :: 2.7
Classifier: Programming Language :: Python :: 3
Classifier: Programming Language :: Python :: 3.2
Classifier: Programming Language :: Python :: 3.3
Classifier: Programming Language :: Python :: 3.4
Classifier: Topic :: Software Development :: Libraries
Classifier: Topic :: Database
Classifier: Topic :: Utilities
